vtk_prompt/__init__.py
vtk_prompt/build_rag_db.py
vtk_prompt/cli.py
vtk_prompt/client.py
vtk_prompt/generate_files.py
vtk_prompt/prompt.py
vtk_prompt/provider_utils.py
vtk_prompt/rag_chat_wrapper.py
vtk_prompt/test_rag.py
vtk_prompt/utils.js
vtk_prompt/vtk_prompt_ui.py
vtk_prompt/prompts/__init__.py
vtk_prompt/prompts/base_context.txt
vtk_prompt/prompts/no_rag_context.txt
vtk_prompt/prompts/python_role.txt
vtk_prompt/prompts/rag_chat_context.txt
vtk_prompt/prompts/rag_context.txt
vtk_prompt/prompts/ui_post_prompt.txt
vtk_prompt/prompts/vtk_xml_context.txt
vtk_prompt/prompts/xml_role.txt
vtk_prompt-0.1.0.dist-info/licenses/LICENSE
vtk_prompt-0.1.0.dist-info/METADATA
vtk_prompt-0.1.0.dist-info/WHEEL
vtk_prompt-0.1.0.dist-info/entry_points.txt
vtk_prompt-0.1.0.dist-info/top_level.txt
vtk_prompt-0.1.0.dist-info/RECORD
