Metadata-Version: 2.4
Name: vtk-prompt
Version: 0.1.0
Summary: A project combining VTK visualization with LLM APIs (Anthropic, OpenAI, NVIDIA NIM)
Author-email: Vicente Adolfo Bolea Sanchez <vicente.bolea@kitware.com>
License-Expression: MIT
Project-URL: Homepage, https://github.com/vicentebolea/vtk-prompt
Project-URL: Repository, https://github.com/vicentebolea/vtk-prompt
Project-URL: Issues, https://github.com/vicentebolea/vtk-prompt/issues
Keywords: vtk,visualization,llm,ai,anthropic,openai
Classifier: Development Status :: 3 - Alpha
Classifier: Intended Audience :: Developers
Classifier: Intended Audience :: Science/Research
Classifier: Operating System :: OS Independent
Classifier: Programming Language :: Python :: 3
Classifier: Programming Language :: Python :: 3.10
Classifier: Programming Language :: Python :: 3.11
Classifier: Programming Language :: Python :: 3.12
Classifier: Topic :: Scientific/Engineering :: Visualization
Classifier: Topic :: Software Development :: Code Generators
Requires-Python: >=3.10
License-File: LICENSE
Requires-Dist: chromadb>=0.6.3
Requires-Dist: click>=8.0.0
Requires-Dist: importlib_resources>=5.0.0
Requires-Dist: llama_index-core>=0.12.17
Requires-Dist: llama-index-llms-anthropic>=0.6.7
Requires-Dist: llama-index-llms-openai>=0.3.20
Requires-Dist: openai>=1.0.0
Requires-Dist: sentence-transformers>=3.4.1
Requires-Dist: tqdm>=4.67.1
Requires-Dist: trame>=3.9.0
Requires-Dist: trame-vtk>=2.8.0
Requires-Dist: trame-vuetify>=3
Requires-Dist: tree_sitter>=0.23
Requires-Dist: tree_sitter_language_pack>=0.7.0
Requires-Dist: tree_sitter_languages>=1.9.1
Requires-Dist: vtk>=9.3.1
Provides-Extra: dev
Requires-Dist: pre-commit; extra == "dev"
Requires-Dist: ruff; extra == "dev"
Requires-Dist: pytest>=6; extra == "dev"
Requires-Dist: pytest-cov>=3; extra == "dev"
Requires-Dist: tox; extra == "dev"
Requires-Dist: black>=23.0.0; extra == "dev"
Requires-Dist: isort>=5.12.0; extra == "dev"
Requires-Dist: flake8>=6.0.0; extra == "dev"
Requires-Dist: flake8-pyproject>=1.2.0; extra == "dev"
Requires-Dist: flake8-docstrings>=1.7.0; extra == "dev"
Requires-Dist: flake8-bugbear>=23.0.0; extra == "dev"
Requires-Dist: flake8-comprehensions>=3.14.0; extra == "dev"
Requires-Dist: mypy>=1.0.0; extra == "dev"
Requires-Dist: types-requests; extra == "dev"
Requires-Dist: types-click; extra == "dev"
Requires-Dist: types-setuptools; extra == "dev"
Provides-Extra: test
Requires-Dist: pytest>=7.0.0; extra == "test"
Requires-Dist: pytest-cov>=4.0.0; extra == "test"
Provides-Extra: all
Requires-Dist: vtk-prompt[dev,test]; extra == "all"
Dynamic: license-file
